web3_async_multi_provider/__init__.py
web3_async_multi_provider/provider.py
web3_async_multi_provider-0.1.0b0.dist-info/LICENSE
web3_async_multi_provider-0.1.0b0.dist-info/METADATA
web3_async_multi_provider-0.1.0b0.dist-info/WHEEL
web3_async_multi_provider-0.1.0b0.dist-info/RECORD
